_meta/__init__.py
nxs_analysis_tools/__init__.py
nxs_analysis_tools/chess.py
nxs_analysis_tools/datareduction.py
nxs_analysis_tools/datasets.py
nxs_analysis_tools/fitting.py
nxs_analysis_tools/lineartransformations.py
nxs_analysis_tools/pairdistribution.py
nxs_analysis_tools-0.1.12.dist-info/licenses/LICENSE
nxs_analysis_tools-0.1.12.dist-info/METADATA
nxs_analysis_tools-0.1.12.dist-info/WHEEL
nxs_analysis_tools-0.1.12.dist-info/top_level.txt
nxs_analysis_tools-0.1.12.dist-info/RECORD
